batchkit/__init__.py
batchkit/apiserver.py
batchkit/audio.py
batchkit/batch_config.py
batchkit/batch_request.py
batchkit/batch_status.py
batchkit/client.py
batchkit/constants.py
batchkit/endpoint_config.py
batchkit/endpoint_manager.py
batchkit/endpoint_status.py
batchkit/handlers.py
batchkit/logger.py
batchkit/orchestrator.py
batchkit/run_summarizer.py
batchkit/utils.py
batchkit/work_item.py
batchkit_examples/__init__.py
batchkit_examples/speech_sdk/__init__.py
batchkit_examples/speech_sdk/audio.py
batchkit_examples/speech_sdk/batch_config.py
batchkit_examples/speech_sdk/batch_request.py
batchkit_examples/speech_sdk/endpoint_status.py
batchkit_examples/speech_sdk/parser.py
batchkit_examples/speech_sdk/recognize.py
batchkit_examples/speech_sdk/run_summarizer.py
batchkit_examples/speech_sdk/work_item.py
batchkit_examples_speechsdk-0.9.1.data/scripts/run-batch-client
batchkit_examples_speechsdk-0.9.1.dist-info/LICENSE
batchkit_examples_speechsdk-0.9.1.dist-info/METADATA
batchkit_examples_speechsdk-0.9.1.dist-info/WHEEL
batchkit_examples_speechsdk-0.9.1.dist-info/top_level.txt
batchkit_examples_speechsdk-0.9.1.dist-info/RECORD
